oasis/__init__.py
oasis/bench/__init__.py
oasis/bench/config.py
oasis/bench/project.py
oasis/bench/utils.py
oasis/bench/core/__init__.py
oasis/bench/core/benchmark.py
oasis/bench/core/common.py
oasis/bench/core/deployment.py
oasis/bench/core/modelpackage.py
oasis/bench/core/compiler/__init__.py
oasis/bench/core/compiler/builder.py
oasis/bench/core/compiler/nnuxe.py
oasis/bench/core/compiler/nnuxe_docker.py
oasis/bench/core/compiler/onnc_saas.py
oasis/bench/core/compiler/saas_config.py
oasis/bench/core/dataset/__init__.py
oasis/bench/core/dataset/dataset.py
oasis/bench/core/dataset/layout.py
oasis/bench/core/dataset/operation.py
oasis/bench/core/dataset/preprocessor.py
oasis/bench/core/dataset/serializer.py
oasis/bench/core/dataset/transformer.py
oasis/bench/core/evaluator/__init__.py
oasis/bench/core/model/__init__.py
oasis/bench/core/model/model.py
oasis/bench/core/model/serializer.py
oasis/bench/core/model/transformer.py
oasis/forest/__init__.py
oasis/forest/core/__init__.py
oasis/forest/core/binding_helper.py
oasis/forest/core/options.py
oasis/forest/core/runtime.py
oasis/forest/proxies/__init__.py
oasis/forest/proxies/zerorpc/__init__.py
oasis/forest/proxies/zerorpc/runtime.py
oasis/forest/proxies/zerorpc/runtime_server.py
oasis/forest/proxies/zerorpc/utils.py
oasis/forest/runtimes/__init__.py
oasis/forest/runtimes/onnx/__init__.py
oasis/forest/runtimes/onnx/runtime.py
oasis/forest/runtimes/openvino/__init__.py
oasis/forest/runtimes/openvino/runtime.py
oasis/forest/runtimes/openvino/utils.py
oasis/forest/runtimes/tensorrt/__init__.py
oasis/forest/runtimes/tensorrt/runtime.py
oasis/forest/runtimes/tensorrt/utils.py
oasis/forest/utils/__init__.py
oasis/forest/utils/load_img.py
oasis_api_client-1.0.0.dist-info/METADATA
oasis_api_client-1.0.0.dist-info/WHEEL
oasis_api_client-1.0.0.dist-info/top_level.txt
oasis_api_client-1.0.0.dist-info/RECORD
