Metadata-Version: 2.1
Name: oasis-api-client
Version: 1.0.0
Summary: OASIS is a Python wrapper of ONNC
Home-page: https://www.skymizer.com
Author: The Skymizer Team
Author-email: hello@skymizer.com
License: Apache License 2.0
Platform: UNKNOWN
Requires-Dist: requests
Requires-Dist: onnx
Requires-Dist: loguru
Requires-Dist: sentry-sdk
Requires-Dist: packaging
Requires-Dist: matplotlib
Requires-Dist: numpy
Requires-Dist: openvino
Requires-Dist: read-only-attributes
Requires-Dist: click
Requires-Dist: wget
Requires-Dist: Jinja2
Requires-Dist: singledispatchmethod
Requires-Dist: msgpack-numpy
Requires-Dist: zerorpc
Requires-Dist: pydlmeta
Requires-Dist: tensorflow (~=2.11)
Requires-Dist: onnxruntime
Requires-Dist: torch
Requires-Dist: torchvision
Requires-Dist: tensorflow-datasets
